DOC_analysis/DOC.py
DOC_analysis/__init__.py
DOC_analysis/diversity.py
DC_analysis-0.1.0.dist-info/LICENSE.txt
DC_analysis-0.1.0.dist-info/METADATA
DC_analysis-0.1.0.dist-info/WHEEL
DC_analysis-0.1.0.dist-info/top_level.txt
DC_analysis-0.1.0.dist-info/RECORD
